Pluginable/Compiler.py
Pluginable/Event.py
Pluginable/Exceptions.py
Pluginable/Executor.py
Pluginable/FileManager.py
Pluginable/LogColor.py
Pluginable/LogOutputs.py
Pluginable/Logger.py
Pluginable/MultiHandler.py
Pluginable/Namespace.py
Pluginable/Plugin.py
Pluginable/Program.py
Pluginable/ProgramOld.py
Pluginable/ProgramStates.py
Pluginable/Settings.py
Pluginable/TpsMonitor.py
Pluginable/__init__.py
mpplugs-0.4.0.dist-info/LICENSE
mpplugs-0.4.0.dist-info/METADATA
mpplugs-0.4.0.dist-info/WHEEL
mpplugs-0.4.0.dist-info/top_level.txt
mpplugs-0.4.0.dist-info/RECORD
