Metadata-Version: 2.1
Name: mpplugs
Version: 0.4.0
Summary: Universal setup+loop framework with multiprocessing support
Home-page: https://github.com/Jakub21/Pluginable
Author: Jakub21
Author-email: UNKNOWN
License: MIT
Platform: UNKNOWN
